README.md
copy_yarn_files.sh
package.json
setup.py
yarn.lock
leverj_ordersigner_test/__init__.py
leverj_ordersigner_test/api.js
leverj_ordersigner_test/api.py
leverj_ordersigner_test.egg-info/PKG-INFO
leverj_ordersigner_test.egg-info/SOURCES.txt
leverj_ordersigner_test.egg-info/dependency_links.txt
leverj_ordersigner_test.egg-info/entry_points.txt
leverj_ordersigner_test.egg-info/requires.txt
leverj_ordersigner_test.egg-info/top_level.txt